LICENSE.md
MANIFEST.in
README.md
setup.cfg
setup.py
uplogic/__init__.py
uplogic/loop.py
uplogic.egg-info/PKG-INFO
uplogic.egg-info/SOURCES.txt
uplogic.egg-info/dependency_links.txt
uplogic.egg-info/requires.txt
uplogic.egg-info/top_level.txt
uplogic.egg-info/zip-safe
uplogic/__pycache__/__init__.cpython-310.pyc
uplogic/__pycache__/__init__.cpython-311.pyc
uplogic/__pycache__/loop.cpython-310.pyc
uplogic/__pycache__/loop.cpython-311.pyc
uplogic/ai/__init__.py
uplogic/ai/agent.py
uplogic/ai/navigation.py
uplogic/ai/__pycache__/__init__.cpython-311.pyc
uplogic/ai/__pycache__/agent.cpython-311.pyc
uplogic/ai/__pycache__/navigation.cpython-311.pyc
uplogic/animation/__init__.py
uplogic/animation/action.py
uplogic/animation/actionsystem.py
uplogic/animation/rig.py
uplogic/animation/sequence.py
uplogic/animation/__pycache__/__init__.cpython-310.pyc
uplogic/animation/__pycache__/__init__.cpython-311.pyc
uplogic/animation/__pycache__/action.cpython-310.pyc
uplogic/animation/__pycache__/action.cpython-311.pyc
uplogic/animation/__pycache__/actionsystem.cpython-310.pyc
uplogic/animation/__pycache__/actionsystem.cpython-311.pyc
uplogic/animation/__pycache__/rig.cpython-310.pyc
uplogic/animation/__pycache__/rig.cpython-311.pyc
uplogic/animation/__pycache__/sequence.cpython-310.pyc
uplogic/animation/__pycache__/sequence.cpython-311.pyc
uplogic/audio/__init__.py
uplogic/audio/audiosystem.py
uplogic/audio/fmod.py
uplogic/audio/music.py
uplogic/audio/sound.py
uplogic/audio/__pycache__/__init__.cpython-310.pyc
uplogic/audio/__pycache__/__init__.cpython-311.pyc
uplogic/audio/__pycache__/audiosystem.cpython-310.pyc
uplogic/audio/__pycache__/audiosystem.cpython-311.pyc
uplogic/audio/__pycache__/fmod.cpython-310.pyc
uplogic/audio/__pycache__/fmod.cpython-311.pyc
uplogic/audio/__pycache__/music.cpython-310.pyc
uplogic/audio/__pycache__/music.cpython-311.pyc
uplogic/audio/__pycache__/sound.cpython-310.pyc
uplogic/audio/__pycache__/sound.cpython-311.pyc
uplogic/console/__init__.py
uplogic/console/__pycache__/__init__.cpython-310.pyc
uplogic/console/__pycache__/__init__.cpython-311.pyc
uplogic/data/__init__.py
uplogic/data/file.py
uplogic/data/globaldb.py
