Metadata-Version: 2.1
Name: uplogic
Version: 5.1.2
Summary: Uplogic utility for UPBGE.
Home-page: https://github.com/UPBGE/uplogic
Author: Leopold Auersperg-Castell
Author-email: lauersperg@gmx.at
License: GPLv2
Download-URL: https://github.com/UPBGE/uplogic/archive/refs/tags/5.1.2.tar.gz
Keywords: Blender UPBGE logic
Platform: UNKNOWN
Classifier: License :: OSI Approved :: GNU General Public License v2 (GPLv2)
Classifier: Intended Audience :: Developers
Classifier: Topic :: Multimedia :: Graphics
Classifier: Programming Language :: Python
Provides-Extra: test
Provides-Extra: docs
License-File: LICENSE.md
